{"title":"项目复盘报告【一】","uid":"48eec35ba806f4293b8f0b679413e7ce","slug":"项目复盘报告【一】","date":"2023-10-01T09:23:29.000Z","updated":"2024-02-13T09:30:51.792Z","comments":true,"path":"api/articles/项目复盘报告【一】.json","keywords":null,"cover":"https://pic.imgdb.cn/item/65cb36a29f345e8d03b81368.jpg","content":"<h2 id=\"前言\"><a href=\"#前言\" class=\"headerlink\" title=\"前言\"></a>前言</h2><p>这是《黑马程序员》推出的一个电商项目的课程，目前项目实现接口 17+，视频教程实际上并没有做完这个项目，大约完成了项目的80%，还有一些功能点没有做好。</p>\n<p>现在我会对之前的项目进度做一个复盘报告。</p>\n<p>同时也会持续进行项目的迭代工作。</p>\n<p>这个电子厂实在是太折磨人了：</p>\n<ol>\n<li>全是水课，没有一节课可以有收获，当然我没有去听课，也逃了很多课，坐在教室很煎熬、痛苦。</li>\n<li>下午无法午休，1点就要去上课。</li>\n<li>很难集中抽出时间自学。</li>\n<li>而且该学校从第十周开始就是考试周了。</li>\n<li>从第十周开始，就要忙期末考试的事情，属于是一周考一场。</li>\n<li>最后课设答辩不规范也是一个很大的问题，两周的时间，浪费时间。</li>\n<li>而且大一一年都是早晚自习，因此基本每一天都被压缩了。</li>\n<li>还有就是军训了将近一个学期（我的感受是这样），我认为让学校的学生来进行教官选拔来进行军训是及其不合规的，是及其不规范的一种行为，是及其不负责任的，学生之间更不应该存在这种上下级关系，属于是不正当的。</li>\n<li>当时也有疫情，做核酸的时候也是及其痛苦的。</li>\n<li>这里的天气也是及其恶劣的。</li>\n</ol>\n<p>但好在：</p>\n<p>老师组织了一个电子科技小组，非常感激老师的用心。说实话，大家来这里只是为了上班，很少会把心思放在学生身上。但是，老师却真心关心我们，这让我感到非常感激。我从心底里感谢老师。如果没有老师组织这个小组，我不知道我现在会是多么糟糕。</p>\n<p>在这里，我结识了很多朋友，收获了许多友谊。我认识了很多努力、积极、有趣、上进的人。这是我这两年来见过的最美妙的风景。我由衷地感谢这一切。</p>\n<p>终于：</p>\n<p>来到了国庆假期</p>\n<p>可以进行复盘工作，看着大佬们的工作总结，洋洋洒洒，反观我自己，实在惭愧，在学校的这 3 个学期里面，没有很大的提高，更多的是内耗与焦虑。</p>\n<p>因此，我要好好反思自己的一切所作所为，好好反省自己。</p>\n<h2 id=\"项目接口文档及演示地址\"><a href=\"#项目接口文档及演示地址\" class=\"headerlink\" title=\"项目接口文档及演示地址\"></a>项目接口文档及演示地址</h2><p><a href=\"https://apifox.com/apidoc/shared-12ab6b18-adc2-444c-ad11-0e60f5693f66/doc-2221080\">接口文档</a></p>\n<p><a href=\"http://cba.itlike.com/public/mweb/#/\">项目演示地址</a></p>\n<h2 id=\"一、项目功能演示\"><a href=\"#一、项目功能演示\" class=\"headerlink\" title=\"一、项目功能演示\"></a>一、项目功能演示</h2><ol>\n<li>明确功能模块</li>\n</ol>\n<p><img src=\"https://pic.imgdb.cn/item/65cacd499f345e8d0396094d.jpg\"></p>\n<ol start=\"2\">\n<li>项目收获</li>\n</ol>\n<p><img src=\"https://pic.imgdb.cn/item/65cad2879f345e8d03a253d6.jpg\"></p>\n<h2 id=\"二、项目创建目录初始化\"><a href=\"#二、项目创建目录初始化\" class=\"headerlink\" title=\"二、项目创建目录初始化\"></a>二、项目创建目录初始化</h2><h3 id=\"vue-cli-建项目\"><a href=\"#vue-cli-建项目\" class=\"headerlink\" title=\"vue-cli 建项目\"></a>vue-cli 建项目</h3><p>1.安装脚手架 (已安装)</p>\n<div class=\"language-bash\"><button title=\"Copy code\" class=\"copy\"></button><span class=\"lang\">bash</span><pre class=\"shiki Aurora Future\" style=\"background-color: #1a1a1a\" tabindex=\"0\"><code><span class=\"line\"><span style=\"color: #9569EC\">npm</span><span style=\"color: #CCCCCC\"> </span><span style=\"color: #CCCCCC\">i</span><span style=\"color: #CCCCCC\"> </span><span style=\"color: #CCCCCC\">@vue/cli</span><span style=\"color: #CCCCCC\"> </span><span style=\"color: #CCCCCC\">-g</span></span></code></pre></div><p>2.创建项目</p>\n<div class=\"language-bash\"><button title=\"Copy code\" class=\"copy\"></button><span class=\"lang\">bash</span><pre class=\"shiki Aurora Future\" style=\"background-color: #1a1a1a\" tabindex=\"0\"><code><span class=\"line\"><span style=\"color: #9569EC\">vue</span><span style=\"color: #CCCCCC\"> </span><span style=\"color: #CCCCCC\">create</span><span style=\"color: #CCCCCC\"> </span><span style=\"color: #CCCCCC\">hm-shopping</span></span></code></pre></div><ul>\n<li>选项</li>\n</ul>\n<div class=\"language-js\"><button title=\"Copy code\" class=\"copy\"></button><span class=\"lang\">js</span><pre class=\"shiki Aurora Future\" style=\"background-color: #1a1a1a\" tabindex=\"0\"><code><span class=\"line\"><span style=\"color: #CCCCCC\">Vue CLI v5</span><span style=\"color: #DA67DA\">.</span><span style=\"color: #9569EC\">0.8</span></span>\n<span class=\"line\"><span style=\"color: #DA67DA\">?</span><span style=\"color: #CCCCCC\"> Please pick a preset</span><span style=\"color: #DA67DA\">:</span></span>\n<span class=\"line\"><span style=\"color: #CCCCCC\">  </span><span style=\"color: #9569EC\">Default</span><span style=\"color: #CCCCCC\"> </span><span style=\"color: #505153\">([</span><span style=\"color: #CCCCCC\">Vue </span><span style=\"color: #9569EC\">3</span><span style=\"color: #505153\">]</span><span style=\"color: #CCCCCC\"> babel</span><span style=\"color: #DA67DA\">,</span><span style=\"color: #CCCCCC\"> eslint</span><span style=\"color: #505153\">)</span></span>\n<span class=\"line\"><span style=\"color: #CCCCCC\">  </span><span style=\"color: #9569EC\">Default</span><span style=\"color: #CCCCCC\"> </span><span style=\"color: #505153\">([</span><span style=\"color: #CCCCCC\">Vue </span><span style=\"color: #9569EC\">2</span><span style=\"color: #505153\">]</span><span style=\"color: #CCCCCC\"> babel</span><span style=\"color: #DA67DA\">,</span><span style=\"color: #CCCCCC\"> eslint</span><span style=\"color: #505153\">)</span></span>\n<span class=\"line\"><span style=\"color: #9569EC\">&gt;</span><span style=\"color: #CCCCCC\"> Manually select features     选自定义</span></span></code></pre></div><ul>\n<li>手动选择功能</li>\n</ul>\n<p><img src=\"https://pic.imgdb.cn/item/65cad4f19f345e8d03a80c63.jpg\"></p>\n<ul>\n<li>选择vue的版本</li>\n</ul>\n<div class=\"language-jsx\"><button title=\"Copy code\" class=\"copy\"></button><span class=\"lang\">jsx</span><pre class=\"shiki Aurora Future\" style=\"background-color: #1a1a1a\" tabindex=\"0\"><code><span class=\"line\"><span style=\"color: #CCCCCC\">  3</span><span style=\"color: #DA67DA\">.</span><span style=\"color: #CCCCCC\">x</span></span>\n<span class=\"line\"><span style=\"color: #9569EC\">&gt;</span><span style=\"color: #CCCCCC\"> 2</span><span style=\"color: #DA67DA\">.</span><span style=\"color: #CCCCCC\">x</span></span></code></pre></div><ul>\n<li>是否使用history模式</li>\n</ul>\n<p><img src=\"https://pic.imgdb.cn/item/65cad5319f345e8d03a8a3aa.jpg\"></p>\n<ul>\n<li>选择css预处理</li>\n</ul>\n<p><img src=\"https://pic.imgdb.cn/item/65cad54b9f345e8d03a8e48e.jpg\"></p>\n<ul>\n<li><p>选择eslint的风格 （eslint 代码规范的检验工具，检验代码是否符合规范）</p>\n</li>\n<li><p>比如：const age &#x3D; 18;   &#x3D;&gt;  报错！多加了分号！后面有工具，一保存，全部格式化成最规范的样子</p>\n</li>\n</ul>\n<p><img src=\"https://pic.imgdb.cn/item/65cad5729f345e8d03a943b5.jpg\"></p>\n<ul>\n<li>选择校验的时机 （直接回车）</li>\n</ul>\n<p><img src=\"https://pic.imgdb.cn/item/65cad5889f345e8d03a979c6.jpg\"></p>\n<ul>\n<li>选择配置文件的生成方式 （直接回车）</li>\n</ul>\n<p><img src=\"https://pic.imgdb.cn/item/65cad5a19f345e8d03a9b925.jpg\"></p>\n<ul>\n<li>是否保存预设，下次直接使用？  &#x3D;&gt;   不保存，输入 N</li>\n</ul>\n<p><img src=\"https://pic.imgdb.cn/item/65cad5be9f345e8d03a9fd55.jpg\"></p>\n<ul>\n<li>等待安装，项目初始化完成</li>\n</ul>\n<p><img src=\"https://pic.imgdb.cn/item/65cad5d69f345e8d03aa34ca.jpg\"></p>\n<ul>\n<li>启动项目</li>\n</ul>\n<div class=\"language-bash\"><button title=\"Copy code\" class=\"copy\"></button><span class=\"lang\">bash</span><pre class=\"shiki Aurora Future\" style=\"background-color: #1a1a1a\" tabindex=\"0\"><code><span class=\"line\"><span style=\"color: #9569EC\">npm</span><span style=\"color: #CCCCCC\"> </span><span style=\"color: #CCCCCC\">run</span><span style=\"color: #CCCCCC\"> </span><span style=\"color: #CCCCCC\">serve</span></span></code></pre></div><h2 id=\"三、调整初始化目录结构\"><a href=\"#三、调整初始化目录结构\" class=\"headerlink\" title=\"三、调整初始化目录结构\"></a>三、调整初始化目录结构</h2><p>为了更好的实现后面的操作，我们把整体的目录结构做一些调整。</p>\n<p>目标:</p>\n<ol>\n<li><p>删除初始化的一些默认文件</p>\n</li>\n<li><p>修改没删除的文件</p>\n</li>\n<li><p>新增我们需要的目录结构</p>\n</li>\n<li><p>删除文件</p>\n</li>\n</ol>\n<ul>\n<li>src&#x2F;assets&#x2F;logo.png</li>\n<li>src&#x2F;components&#x2F;HelloWorld.vue</li>\n<li>src&#x2F;views&#x2F;AboutView.vue</li>\n<li>src&#x2F;views&#x2F;HomeView.vue</li>\n</ul>\n<ol start=\"2\">\n<li>修改文件</li>\n</ol>\n<p><code>main.js</code> 不需要修改</p>\n<p><code>router/index.js</code></p>\n<p>删除默认的路由配置</p>\n<div class=\"language-javascript\"><button title=\"Copy code\" class=\"copy\"></button><span class=\"lang\">javascript</span><pre class=\"shiki Aurora Future\" style=\"background-color: #1a1a1a\" tabindex=\"0\"><code><span class=\"line\"><span style=\"color: #9569EC\">import</span><span style=\"color: #CCCCCC\"> Vue </span><span style=\"color: #9569EC\">from</span><span style=\"color: #CCCCCC\"> </span><span style=\"color: #505153\">&#39;</span><span style=\"color: #DA67DA\">vue</span><span style=\"color: #505153\">&#39;</span></span>\n<span class=\"line\"><span style=\"color: #9569EC\">import</span><span style=\"color: #CCCCCC\"> VueRouter </span><span style=\"color: #9569EC\">from</span><span style=\"color: #CCCCCC\"> </span><span style=\"color: #505153\">&#39;</span><span style=\"color: #DA67DA\">vue-router</span><span style=\"color: #505153\">&#39;</span></span>\n<span class=\"line\"><span style=\"color: #61D0FF\">Vue</span><span style=\"color: #DA67DA\">.</span><span style=\"color: #9569EC\">use</span><span style=\"color: #505153\">(</span><span style=\"color: #CCCCCC\">VueRouter</span><span style=\"color: #505153\">)</span></span>\n<span class=\"line\"><span style=\"color: #DA67DA\">const</span><span style=\"color: #CCCCCC\"> routes </span><span style=\"color: #9569EC\">=</span><span style=\"color: #CCCCCC\"> </span><span style=\"color: #505153\">[</span></span>\n<span class=\"line\"><span style=\"color: #505153\">]</span></span>\n<span class=\"line\"><span style=\"color: #DA67DA\">const</span><span style=\"color: #CCCCCC\"> router </span><span style=\"color: #9569EC\">=</span><span style=\"color: #CCCCCC\"> </span><span style=\"color: #9569EC\">new</span><span style=\"color: #CCCCCC\"> </span><span style=\"color: #9569EC\">VueRouter</span><span style=\"color: #505153\">(&#123;</span></span>\n<span class=\"line\"><span style=\"color: #CCCCCC\">  routes</span></span>\n<span class=\"line\"><span style=\"color: #505153\">&#125;)</span></span>\n<span class=\"line\"><span style=\"color: #9569EC\">export</span><span style=\"color: #CCCCCC\"> </span><span style=\"color: #9569EC\">default</span><span style=\"color: #CCCCCC\"> router</span></span></code></pre></div><p><code>App.vue</code></p>\n<div class=\"language-html\"><button title=\"Copy code\" class=\"copy\"></button><span class=\"lang\">html</span><pre class=\"shiki Aurora Future\" style=\"background-color: #1a1a1a\" tabindex=\"0\"><code><span class=\"line\"><span style=\"color: #DA67DA\">&lt;</span><span style=\"color: #9569EC; font-style: italic\">template</span><span style=\"color: #DA67DA\">&gt;</span></span>\n<span class=\"line\"><span style=\"color: #CCCCCC\">  </span><span style=\"color: #DA67DA\">&lt;</span><span style=\"color: #9569EC; font-style: italic\">div</span><span style=\"color: #CCCCCC\"> </span><span style=\"color: #61D0FF\">id</span><span style=\"color: #505153\">=</span><span style=\"color: #505153\">&quot;</span><span style=\"color: #CCCCCC\">app</span><span style=\"color: #505153\">&quot;</span><span style=\"color: #DA67DA\">&gt;</span></span>\n<span class=\"line\"><span style=\"color: #CCCCCC\">    </span><span style=\"color: #DA67DA\">&lt;</span><span style=\"color: #9569EC; font-style: italic\">router-view</span><span style=\"color: #DA67DA\">/&gt;</span></span>\n<span class=\"line\"><span style=\"color: #CCCCCC\">  </span><span style=\"color: #DA67DA\">&lt;/</span><span style=\"color: #9569EC; font-style: italic\">div</span><span style=\"color: #DA67DA\">&gt;</span></span>\n<span class=\"line\"><span style=\"color: #DA67DA\">&lt;/</span><span style=\"color: #9569EC; font-style: italic\">template</span><span style=\"color: #DA67DA\">&gt;</span></span></code></pre></div><ol start=\"3\">\n<li>新增目录</li>\n</ol>\n<ul>\n<li>src &#x2F; api 目录<ul>\n<li>存储接口模块</li>\n</ul>\n</li>\n<li>src &#x2F; utils 目录<ul>\n<li>存储一些工具模块</li>\n</ul>\n</li>\n</ul>\n<p>目录效果如下 :</p>\n<p><img src=\"https://pic.imgdb.cn/item/65cad8ca9f345e8d03b14e75.jpg\"></p>\n<h2 id=\"四、vant组件库及Vue周边的其它组件库\"><a href=\"#四、vant组件库及Vue周边的其它组件库\" class=\"headerlink\" title=\"四、vant组件库及Vue周边的其它组件库\"></a>四、vant组件库及Vue周边的其它组件库</h2><p><a href=\"%5Bhttps://vant-contrib.gitee.io/vant/v2/#/zh-CN/%5D(https://vant-contrib.gitee.io/vant/v2/#/zh-CN/)\">Vant 组件库</a></p>\n<p><img src=\"https://pic.imgdb.cn/item/65cad98f9f345e8d03b3325a.jpg\"></p>\n<p>比如日历组件、键盘组件、打分组件、下拉筛选组件等</p>\n<p>组件库并不是唯一的，常用的组件库还有以下几种：</p>\n<p>pc: <a href=\"https://gitee.com/link?target=https://element.eleme.cn/%23/zh-CN\">element-ui</a> <a href=\"https://element-plus.gitee.io/zh-CN/\">element-plus</a> <a href=\"https://gitee.com/link?target=https://iview.github.io/\">iview</a> <strong><a href=\"https://gitee.com/link?target=https://antdv.com/components/overview-cn\">ant-design</a></strong></p>\n<p>移动：<a href=\"https://vant-contrib.gitee.io/vant/v2/#/zh-CN/\">vant-ui</a> <a href=\"https://gitee.com/link?target=http://mint-ui.github.io/docs/%23/zh-cn2\">Mint UI</a> (饿了么) <a href=\"https://gitee.com/link?target=https://didi.github.io/cube-ui/%23/zh-CN/\">Cube UI</a> (滴滴)</p>\n<h2 id=\"五、全部导入和按需导入的区别\"><a href=\"#五、全部导入和按需导入的区别\" class=\"headerlink\" title=\"五、全部导入和按需导入的区别\"></a>五、全部导入和按需导入的区别</h2><p>目标：明确 <strong>全部导入</strong> 和 <strong>按需导入</strong> 的区别</p>\n<p><img src=\"https://pic.imgdb.cn/item/65cada3b9f345e8d03b4ceae.jpg\"><br>区别：</p>\n<ol>\n<li><p>全部导入会引起项目打包后的体积变大，进而影响用户访问网站的性能</p>\n</li>\n<li><p>按需导入只会导入你使用的组件，进而节约了资源</p>\n</li>\n</ol>\n<h2 id=\"六、全部导入\"><a href=\"#六、全部导入\" class=\"headerlink\" title=\"六、全部导入\"></a>六、全部导入</h2><p>安装 vant-ui</p>\n<div class=\"language-bash\"><button title=\"Copy code\" class=\"copy\"></button><span class=\"lang\">bash</span><pre class=\"shiki Aurora Future\" style=\"background-color: #1a1a1a\" tabindex=\"0\"><code><span class=\"line\"><span style=\"color: #9569EC\">yarn</span><span style=\"color: #CCCCCC\"> </span><span style=\"color: #CCCCCC\">add</span><span style=\"color: #CCCCCC\"> </span><span style=\"color: #CCCCCC\">vant@latest-v2</span></span></code></pre></div><p>在 main.js 中</p>\n<div class=\"language-javascript\"><button title=\"Copy code\" class=\"copy\"></button><span class=\"lang\">javascript</span><pre class=\"shiki Aurora Future\" style=\"background-color: #1a1a1a\" tabindex=\"0\"><code><span class=\"line\"><span style=\"color: #9569EC\">import</span><span style=\"color: #CCCCCC\"> Vant </span><span style=\"color: #9569EC\">from</span><span style=\"color: #CCCCCC\"> </span><span style=\"color: #505153\">&#39;</span><span style=\"color: #DA67DA\">vant</span><span style=\"color: #505153\">&#39;</span></span>\n<span class=\"line\"><span style=\"color: #9569EC\">import</span><span style=\"color: #CCCCCC\"> </span><span style=\"color: #505153\">&#39;</span><span style=\"color: #DA67DA\">vant/lib/index.css</span><span style=\"color: #505153\">&#39;</span></span>\n<span class=\"line\"><span style=\"color: #61D0FF\">Vue</span><span style=\"color: #DA67DA\">.</span><span style=\"color: #9569EC\">use</span><span style=\"color: #505153\">(</span><span style=\"color: #CCCCCC\">Vant</span><span style=\"color: #505153\">)</span></span></code></pre></div><p>直接使用</p>\n<div class=\"language-html\"><button title=\"Copy code\" class=\"copy\"></button><span class=\"lang\">html</span><pre class=\"shiki Aurora Future\" style=\"background-color: #1a1a1a\" tabindex=\"0\"><code><span class=\"line\"><span style=\"color: #DA67DA\">&lt;</span><span style=\"color: #9569EC; font-style: italic\">van-button</span><span style=\"color: #CCCCCC\"> </span><span style=\"color: #61D0FF\">type</span><span style=\"color: #505153\">=</span><span style=\"color: #505153\">&quot;</span><span style=\"color: #CCCCCC\">primary</span><span style=\"color: #505153\">&quot;</span><span style=\"color: #DA67DA\">&gt;</span><span style=\"color: #CCCCCC\">主要按钮</span><span style=\"color: #DA67DA\">&lt;/</span><span style=\"color: #9569EC; font-style: italic\">van-button</span><span style=\"color: #DA67DA\">&gt;</span></span>\n<span class=\"line\"><span style=\"color: #DA67DA\">&lt;</span><span style=\"color: #9569EC; font-style: italic\">van-button</span><span style=\"color: #CCCCCC\"> </span><span style=\"color: #61D0FF\">type</span><span style=\"color: #505153\">=</span><span style=\"color: #505153\">&quot;</span><span style=\"color: #CCCCCC\">info</span><span style=\"color: #505153\">&quot;</span><span style=\"color: #DA67DA\">&gt;</span><span style=\"color: #CCCCCC\">信息按钮</span><span style=\"color: #DA67DA\">&lt;/</span><span style=\"color: #9569EC; font-style: italic\">van-button</span><span style=\"color: #DA67DA\">&gt;</span></span></code></pre></div><h2 id=\"七、按需导入\"><a href=\"#七、按需导入\" class=\"headerlink\" title=\"七、按需导入\"></a>七、按需导入</h2><ul>\n<li>安装vant-ui</li>\n</ul>\n<div class=\"language-bash\"><button title=\"Copy code\" class=\"copy\"></button><span class=\"lang\">bash</span><pre class=\"shiki Aurora Future\" style=\"background-color: #1a1a1a\" tabindex=\"0\"><code><span class=\"line\"><span style=\"color: #9569EC\">yarn</span><span style=\"color: #CCCCCC\"> </span><span style=\"color: #CCCCCC\">add</span><span style=\"color: #CCCCCC\"> </span><span style=\"color: #CCCCCC\">vant@latest-v2</span></span></code></pre></div><ul>\n<li>安装一个插件</li>\n</ul>\n<div class=\"language-bash\"><button title=\"Copy code\" class=\"copy\"></button><span class=\"lang\">bash</span><pre class=\"shiki Aurora Future\" style=\"background-color: #1a1a1a\" tabindex=\"0\"><code><span class=\"line\"><span style=\"color: #9569EC\">yarn</span><span style=\"color: #CCCCCC\"> </span><span style=\"color: #CCCCCC\">add</span><span style=\"color: #CCCCCC\"> </span><span style=\"color: #CCCCCC\">babel-plugin-import</span><span style=\"color: #CCCCCC\"> </span><span style=\"color: #CCCCCC\">-D</span></span></code></pre></div><ul>\n<li>在<code>babel.config.js</code>中配置</li>\n</ul>\n<div class=\"language-javascript\"><button title=\"Copy code\" class=\"copy\"></button><span class=\"lang\">javascript</span><pre class=\"shiki Aurora Future\" style=\"background-color: #1a1a1a\" tabindex=\"0\"><code><span class=\"line\"><span style=\"color: #9569EC; font-style: italic\">module</span><span style=\"color: #DA67DA\">.</span><span style=\"color: #9569EC; font-style: italic\">exports</span><span style=\"color: #CCCCCC\"> </span><span style=\"color: #9569EC\">=</span><span style=\"color: #CCCCCC\"> </span><span style=\"color: #505153\">&#123;</span></span>\n<span class=\"line\"><span style=\"color: #CCCCCC\">  presets</span><span style=\"color: #DA67DA\">:</span><span style=\"color: #CCCCCC\"> </span><span style=\"color: #505153\">[</span></span>\n<span class=\"line\"><span style=\"color: #CCCCCC\">    </span><span style=\"color: #505153\">&#39;</span><span style=\"color: #CCCCCC\">@vue/cli-plugin-babel/preset</span><span style=\"color: #505153\">&#39;</span></span>\n<span class=\"line\"><span style=\"color: #CCCCCC\">  </span><span style=\"color: #505153\">]</span><span style=\"color: #DA67DA\">,</span></span>\n<span class=\"line\"><span style=\"color: #CCCCCC\">  plugins</span><span style=\"color: #DA67DA\">:</span><span style=\"color: #CCCCCC\"> </span><span style=\"color: #505153\">[</span></span>\n<span class=\"line\"><span style=\"color: #CCCCCC\">    </span><span style=\"color: #505153\">[</span><span style=\"color: #505153\">&#39;</span><span style=\"color: #CCCCCC\">import</span><span style=\"color: #505153\">&#39;</span><span style=\"color: #DA67DA\">,</span><span style=\"color: #CCCCCC\"> </span><span style=\"color: #505153\">&#123;</span></span>\n<span class=\"line\"><span style=\"color: #CCCCCC\">      libraryName</span><span style=\"color: #DA67DA\">:</span><span style=\"color: #CCCCCC\"> </span><span style=\"color: #505153\">&#39;</span><span style=\"color: #CCCCCC\">vant</span><span style=\"color: #505153\">&#39;</span><span style=\"color: #DA67DA\">,</span></span>\n<span class=\"line\"><span style=\"color: #CCCCCC\">      libraryDirectory</span><span style=\"color: #DA67DA\">:</span><span style=\"color: #CCCCCC\"> </span><span style=\"color: #505153\">&#39;</span><span style=\"color: #CCCCCC\">es</span><span style=\"color: #505153\">&#39;</span><span style=\"color: #DA67DA\">,</span></span>\n<span class=\"line\"><span style=\"color: #CCCCCC\">      style</span><span style=\"color: #DA67DA\">:</span><span style=\"color: #CCCCCC\"> </span><span style=\"color: #9569EC; font-style: italic\">true</span></span>\n<span class=\"line\"><span style=\"color: #CCCCCC\">    </span><span style=\"color: #505153\">&#125;</span><span style=\"color: #DA67DA\">,</span><span style=\"color: #CCCCCC\"> </span><span style=\"color: #505153\">&#39;</span><span style=\"color: #CCCCCC\">vant</span><span style=\"color: #505153\">&#39;</span><span style=\"color: #505153\">]</span></span>\n<span class=\"line\"><span style=\"color: #CCCCCC\">  </span><span style=\"color: #505153\">]</span></span>\n<span class=\"line\"><span style=\"color: #505153\">&#125;</span></span></code></pre></div><ul>\n<li>按需加载，在<code>main.js</code></li>\n</ul>\n<div class=\"language-javascript\"><button title=\"Copy code\" class=\"copy\"></button><span class=\"lang\">javascript</span><pre class=\"shiki Aurora Future\" style=\"background-color: #1a1a1a\" tabindex=\"0\"><code><span class=\"line\"><span style=\"color: #9569EC\">import</span><span style=\"color: #CCCCCC\"> </span><span style=\"color: #505153\">&#123;</span><span style=\"color: #CCCCCC\"> Button</span><span style=\"color: #61D0FF\">,</span><span style=\"color: #CCCCCC\"> Icon </span><span style=\"color: #505153\">&#125;</span><span style=\"color: #CCCCCC\"> </span><span style=\"color: #9569EC\">from</span><span style=\"color: #CCCCCC\"> </span><span style=\"color: #505153\">&#39;</span><span style=\"color: #DA67DA\">vant</span><span style=\"color: #505153\">&#39;</span></span>\n<span class=\"line\"><span style=\"color: #61D0FF\">Vue</span><span style=\"color: #DA67DA\">.</span><span style=\"color: #9569EC\">use</span><span style=\"color: #505153\">(</span><span style=\"color: #CCCCCC\">Button</span><span style=\"color: #505153\">)</span></span>\n<span class=\"line\"><span style=\"color: #61D0FF\">Vue</span><span style=\"color: #DA67DA\">.</span><span style=\"color: #9569EC\">use</span><span style=\"color: #505153\">(</span><span style=\"color: #CCCCCC\">Icon</span><span style=\"color: #505153\">)</span></span></code></pre></div><ul>\n<li><code>app.vue</code>中进行测试</li>\n</ul>\n<div class=\"language-html\"><button title=\"Copy code\" class=\"copy\"></button><span class=\"lang\">html</span><pre class=\"shiki Aurora Future\" style=\"background-color: #1a1a1a\" tabindex=\"0\"><code><span class=\"line\"><span style=\"color: #DA67DA\">&lt;</span><span style=\"color: #9569EC; font-style: italic\">van-button</span><span style=\"color: #CCCCCC\"> </span><span style=\"color: #61D0FF\">type</span><span style=\"color: #505153\">=</span><span style=\"color: #505153\">&quot;</span><span style=\"color: #CCCCCC\">primary</span><span style=\"color: #505153\">&quot;</span><span style=\"color: #DA67DA\">&gt;</span><span style=\"color: #CCCCCC\">主要按钮</span><span style=\"color: #DA67DA\">&lt;/</span><span style=\"color: #9569EC; font-style: italic\">van-button</span><span style=\"color: #DA67DA\">&gt;</span></span>\n<span class=\"line\"><span style=\"color: #DA67DA\">&lt;</span><span style=\"color: #9569EC; font-style: italic\">van-button</span><span style=\"color: #CCCCCC\"> </span><span style=\"color: #61D0FF\">type</span><span style=\"color: #505153\">=</span><span style=\"color: #505153\">&quot;</span><span style=\"color: #CCCCCC\">info</span><span style=\"color: #505153\">&quot;</span><span style=\"color: #DA67DA\">&gt;</span><span style=\"color: #CCCCCC\">信息按钮</span><span style=\"color: #DA67DA\">&lt;/</span><span style=\"color: #9569EC; font-style: italic\">van-button</span><span style=\"color: #DA67DA\">&gt;</span></span>\n<span class=\"line\"><span style=\"color: #DA67DA\">&lt;</span><span style=\"color: #9569EC; font-style: italic\">van-button</span><span style=\"color: #CCCCCC\"> </span><span style=\"color: #61D0FF\">type</span><span style=\"color: #505153\">=</span><span style=\"color: #505153\">&quot;</span><span style=\"color: #CCCCCC\">default</span><span style=\"color: #505153\">&quot;</span><span style=\"color: #DA67DA\">&gt;</span><span style=\"color: #CCCCCC\">默认按钮</span><span style=\"color: #DA67DA\">&lt;/</span><span style=\"color: #9569EC; font-style: italic\">van-button</span><span style=\"color: #DA67DA\">&gt;</span></span>\n<span class=\"line\"><span style=\"color: #DA67DA\">&lt;</span><span style=\"color: #9569EC; font-style: italic\">van-button</span><span style=\"color: #CCCCCC\"> </span><span style=\"color: #61D0FF\">type</span><span style=\"color: #505153\">=</span><span style=\"color: #505153\">&quot;</span><span style=\"color: #CCCCCC\">warning</span><span style=\"color: #505153\">&quot;</span><span style=\"color: #DA67DA\">&gt;</span><span style=\"color: #CCCCCC\">警告按钮</span><span style=\"color: #DA67DA\">&lt;/</span><span style=\"color: #9569EC; font-style: italic\">van-button</span><span style=\"color: #DA67DA\">&gt;</span></span>\n<span class=\"line\"><span style=\"color: #DA67DA\">&lt;</span><span style=\"color: #9569EC; font-style: italic\">van-button</span><span style=\"color: #CCCCCC\"> </span><span style=\"color: #61D0FF\">type</span><span style=\"color: #505153\">=</span><span style=\"color: #505153\">&quot;</span><span style=\"color: #CCCCCC\">danger</span><span style=\"color: #505153\">&quot;</span><span style=\"color: #DA67DA\">&gt;</span><span style=\"color: #CCCCCC\">危险按钮</span><span style=\"color: #DA67DA\">&lt;/</span><span style=\"color: #9569EC; font-style: italic\">van-button</span><span style=\"color: #DA67DA\">&gt;</span></span></code></pre></div><ul>\n<li>把引入组件的步骤抽离到单独的js文件中比如 <code>utils/vant-ui.js</code></li>\n</ul>\n<div class=\"language-javascript\"><button title=\"Copy code\" class=\"copy\"></button><span class=\"lang\">javascript</span><pre class=\"shiki Aurora Future\" style=\"background-color: #1a1a1a\" tabindex=\"0\"><code><span class=\"line\"><span style=\"color: #9569EC\">import</span><span style=\"color: #CCCCCC\"> </span><span style=\"color: #505153\">&#123;</span><span style=\"color: #CCCCCC\"> Button</span><span style=\"color: #61D0FF\">,</span><span style=\"color: #CCCCCC\"> Icon </span><span style=\"color: #505153\">&#125;</span><span style=\"color: #CCCCCC\"> </span><span style=\"color: #9569EC\">from</span><span style=\"color: #CCCCCC\"> </span><span style=\"color: #505153\">&#39;</span><span style=\"color: #DA67DA\">vant</span><span style=\"color: #505153\">&#39;</span></span>\n<span class=\"line\"><span style=\"color: #61D0FF\">Vue</span><span style=\"color: #DA67DA\">.</span><span style=\"color: #9569EC\">use</span><span style=\"color: #505153\">(</span><span style=\"color: #CCCCCC\">Button</span><span style=\"color: #505153\">)</span></span>\n<span class=\"line\"><span style=\"color: #61D0FF\">Vue</span><span style=\"color: #DA67DA\">.</span><span style=\"color: #9569EC\">use</span><span style=\"color: #505153\">(</span><span style=\"color: #CCCCCC\">Icon</span><span style=\"color: #505153\">)</span></span></code></pre></div><ul>\n<li>main.js中进行导入</li>\n</ul>\n<div class=\"language-javascript\"><button title=\"Copy code\" class=\"copy\"></button><span class=\"lang\">javascript</span><pre class=\"shiki Aurora Future\" style=\"background-color: #1a1a1a\" tabindex=\"0\"><code><span class=\"line\"><span style=\"color: #65666B; font-style: italic\">// 导入按需导入的配置文件</span></span>\n<span class=\"line\"><span style=\"color: #9569EC\">import</span><span style=\"color: #CCCCCC\"> </span><span style=\"color: #505153\">&#39;</span><span style=\"color: #DA67DA\">@/utils/vant-ui</span><span style=\"color: #505153\">&#39;</span></span></code></pre></div><h2 id=\"八、项目中的-vw-适配\"><a href=\"#八、项目中的-vw-适配\" class=\"headerlink\" title=\"八、项目中的 vw 适配\"></a>八、项目中的 vw 适配</h2><p><a href=\"%5Bhttps://vant-contrib.gitee.io/vant/v2/#/zh-CN/advanced-usage%5D(https://vant-contrib.gitee.io/vant/v2/#/zh-CN/advanced-usage)\">官方说明</a></p>\n<div class=\"language-bash\"><button title=\"Copy code\" class=\"copy\"></button><span class=\"lang\">bash</span><pre class=\"shiki Aurora Future\" style=\"background-color: #1a1a1a\" tabindex=\"0\"><code><span class=\"line\"><span style=\"color: #9569EC\">yarn</span><span style=\"color: #CCCCCC\"> </span><span style=\"color: #CCCCCC\">add</span><span style=\"color: #CCCCCC\"> </span><span style=\"color: #CCCCCC\">postcss-px-to-viewport@1.1.1</span><span style=\"color: #CCCCCC\"> </span><span style=\"color: #CCCCCC\">-D</span></span></code></pre></div><ul>\n<li>项目根目录， 新建postcss的配置文件<code>postcss.config.js</code></li>\n</ul>\n<div class=\"language-javascript\"><button title=\"Copy code\" class=\"copy\"></button><span class=\"lang\">javascript</span><pre class=\"shiki Aurora Future\" style=\"background-color: #1a1a1a\" tabindex=\"0\"><code><span class=\"line\"><span style=\"color: #9569EC; font-style: italic\">module</span><span style=\"color: #DA67DA\">.</span><span style=\"color: #9569EC; font-style: italic\">exports</span><span style=\"color: #CCCCCC\"> </span><span style=\"color: #9569EC\">=</span><span style=\"color: #CCCCCC\"> </span><span style=\"color: #505153\">&#123;</span></span>\n<span class=\"line\"><span style=\"color: #CCCCCC\">  plugins</span><span style=\"color: #DA67DA\">:</span><span style=\"color: #CCCCCC\"> </span><span style=\"color: #505153\">&#123;</span></span>\n<span class=\"line\"><span style=\"color: #CCCCCC\">    </span><span style=\"color: #505153\">&#39;</span><span style=\"color: #CCCCCC\">postcss-px-to-viewport</span><span style=\"color: #505153\">&#39;</span><span style=\"color: #DA67DA\">:</span><span style=\"color: #CCCCCC\"> </span><span style=\"color: #505153\">&#123;</span></span>\n<span class=\"line\"><span style=\"color: #CCCCCC\">      viewportWidth</span><span style=\"color: #DA67DA\">:</span><span style=\"color: #CCCCCC\"> </span><span style=\"color: #9569EC\">375</span><span style=\"color: #DA67DA\">,</span></span>\n<span class=\"line\"><span style=\"color: #CCCCCC\">    </span><span style=\"color: #505153\">&#125;</span><span style=\"color: #DA67DA\">,</span></span>\n<span class=\"line\"><span style=\"color: #CCCCCC\">  </span><span style=\"color: #505153\">&#125;</span><span style=\"color: #DA67DA\">,</span></span>\n<span class=\"line\"><span style=\"color: #505153\">&#125;;</span></span></code></pre></div><p>viewportWidth:设计稿的视口宽度</p>\n<ol>\n<li>vant-ui中的组件就是按照375的视口宽度设计的</li>\n<li>恰好面经项目中的设计稿也是按照375的视口宽度设计的，所以此时 我们只需要配置375就可以了</li>\n<li>如果设计稿不是按照375而是按照750的宽度设计，<a href=\"https://gitee.com/link?target=https://zhuanlan.zhihu.com/p/366664788\">那此时这个值该怎么填呢？</a></li>\n</ol>\n<h2 id=\"结语\"><a href=\"#结语\" class=\"headerlink\" title=\"结语\"></a>结语</h2><p>学如逆水行舟，不进则退</p>\n<p><code>2023</code> <code>10</code> <code>1</code></p>\n","text":"前言这是《黑马程序员》推出的一个电商项目的课程，目前项目实现接口 17+，视频教程实际上并没有做完这个项目，大约完成了项目的80%，还有一些功能点没有做好。 现...","permalink":"/post/项目复盘报告【一】","photos":[],"count_time":{"symbolsCount":"4k","symbolsTime":"4 mins."},"categories":[{"name":"智慧商城项目","slug":"智慧商城项目","count":7,"path":"api/categories/智慧商城项目.json"}],"tags":[{"name":"项目","slug":"项目","count":7,"path":"api/tags/项目.json"}],"toc":"<ol class=\"toc\"><li class=\"toc-item toc-level-2\"><a class=\"toc-link\" href=\"#%E5%89%8D%E8%A8%80\"><span class=\"toc-text\">前言</span></a></li><li class=\"toc-item toc-level-2\"><a class=\"toc-link\" href=\"#%E9%A1%B9%E7%9B%AE%E6%8E%A5%E5%8F%A3%E6%96%87%E6%A1%A3%E5%8F%8A%E6%BC%94%E7%A4%BA%E5%9C%B0%E5%9D%80\"><span class=\"toc-text\">项目接口文档及演示地址</span></a></li><li class=\"toc-item toc-level-2\"><a class=\"toc-link\" href=\"#%E4%B8%80%E3%80%81%E9%A1%B9%E7%9B%AE%E5%8A%9F%E8%83%BD%E6%BC%94%E7%A4%BA\"><span class=\"toc-text\">一、项目功能演示</span></a></li><li class=\"toc-item toc-level-2\"><a class=\"toc-link\" href=\"#%E4%BA%8C%E3%80%81%E9%A1%B9%E7%9B%AE%E5%88%9B%E5%BB%BA%E7%9B%AE%E5%BD%95%E5%88%9D%E5%A7%8B%E5%8C%96\"><span class=\"toc-text\">二、项目创建目录初始化</span></a><ol class=\"toc-child\"><li class=\"toc-item toc-level-3\"><a class=\"toc-link\" href=\"#vue-cli-%E5%BB%BA%E9%A1%B9%E7%9B%AE\"><span class=\"toc-text\">vue-cli 建项目</span></a></li></ol></li><li class=\"toc-item toc-level-2\"><a class=\"toc-link\" href=\"#%E4%B8%89%E3%80%81%E8%B0%83%E6%95%B4%E5%88%9D%E5%A7%8B%E5%8C%96%E7%9B%AE%E5%BD%95%E7%BB%93%E6%9E%84\"><span class=\"toc-text\">三、调整初始化目录结构</span></a></li><li class=\"toc-item toc-level-2\"><a class=\"toc-link\" href=\"#%E5%9B%9B%E3%80%81vant%E7%BB%84%E4%BB%B6%E5%BA%93%E5%8F%8AVue%E5%91%A8%E8%BE%B9%E7%9A%84%E5%85%B6%E5%AE%83%E7%BB%84%E4%BB%B6%E5%BA%93\"><span class=\"toc-text\">四、vant组件库及Vue周边的其它组件库</span></a></li><li class=\"toc-item toc-level-2\"><a class=\"toc-link\" href=\"#%E4%BA%94%E3%80%81%E5%85%A8%E9%83%A8%E5%AF%BC%E5%85%A5%E5%92%8C%E6%8C%89%E9%9C%80%E5%AF%BC%E5%85%A5%E7%9A%84%E5%8C%BA%E5%88%AB\"><span class=\"toc-text\">五、全部导入和按需导入的区别</span></a></li><li class=\"toc-item toc-level-2\"><a class=\"toc-link\" href=\"#%E5%85%AD%E3%80%81%E5%85%A8%E9%83%A8%E5%AF%BC%E5%85%A5\"><span class=\"toc-text\">六、全部导入</span></a></li><li class=\"toc-item toc-level-2\"><a class=\"toc-link\" href=\"#%E4%B8%83%E3%80%81%E6%8C%89%E9%9C%80%E5%AF%BC%E5%85%A5\"><span class=\"toc-text\">七、按需导入</span></a></li><li class=\"toc-item toc-level-2\"><a class=\"toc-link\" href=\"#%E5%85%AB%E3%80%81%E9%A1%B9%E7%9B%AE%E4%B8%AD%E7%9A%84-vw-%E9%80%82%E9%85%8D\"><span class=\"toc-text\">八、项目中的 vw 适配</span></a></li><li class=\"toc-item toc-level-2\"><a class=\"toc-link\" href=\"#%E7%BB%93%E8%AF%AD\"><span class=\"toc-text\">结语</span></a></li></ol>","author":{"name":"一小池勺","slug":"blog-author","avatar":"https://pic.imgdb.cn/item/65c339bd9f345e8d03bb301d.jpg","link":"/","description":"不要感受路，要赶路","socials":{"github":"https://gitee.com/zrblue","twitter":"","stackoverflow":"","wechat":"","qq":"","weibo":"https://weibo.com/u/3318213455","zhihu":"","csdn":"https://blog.csdn.net/zrblue?type=blog","juejin":"https://juejin.cn","customs":{}}},"mapped":true,"hidden":false,"prev_post":{"title":"项目复盘报告【二】","uid":"c9c880b5a5547e09fadebe0f84b91ba0","slug":"项目复盘报告【二】","date":"2023-10-02T09:23:42.000Z","updated":"2024-02-13T09:31:15.102Z","comments":true,"path":"api/articles/项目复盘报告【二】.json","keywords":null,"cover":"https://pic.imgdb.cn/item/65cb36a29f345e8d03b81368.jpg","text":"一、路由配置 - 一级路由但凡是单个页面，独立展示的，都是一级路由 路由设计： 登录页 首页架子 首页 - 二级 分类页 - 二级 购物车 - 二级 我的 - ...","permalink":"/post/项目复盘报告【二】","photos":[],"count_time":{"symbolsCount":"8.8k","symbolsTime":"8 mins."},"categories":[{"name":"智慧商城项目","slug":"智慧商城项目","count":7,"path":"api/categories/智慧商城项目.json"}],"tags":[{"name":"项目","slug":"项目","count":7,"path":"api/tags/项目.json"}],"author":{"name":"一小池勺","slug":"blog-author","avatar":"https://pic.imgdb.cn/item/65c339bd9f345e8d03bb301d.jpg","link":"/","description":"不要感受路，要赶路","socials":{"github":"https://gitee.com/zrblue","twitter":"","stackoverflow":"","wechat":"","qq":"","weibo":"https://weibo.com/u/3318213455","zhihu":"","csdn":"https://blog.csdn.net/zrblue?type=blog","juejin":"https://juejin.cn","customs":{}}}},"next_post":{"title":"前端框架开发【九】实现过渡动画","uid":"90b0cd7f9ee3294d68bd40236729dc06","slug":"前端框架开发【九】实现过渡动画","date":"2023-09-20T02:57:36.000Z","updated":"2024-02-11T03:11:18.265Z","comments":true,"path":"api/articles/前端框架开发【九】实现过渡动画.json","keywords":null,"cover":"https://pic.imgdb.cn/item/65c839ff9f345e8d03c8fec9.jpg","text":"1. 基本过渡动画1.1. 认识过渡动画在开发中，我们想要给一个组件的显示和消失添加某种过渡动画，可以很好的增加用户体验： React框架本身并没有提供任何动画...","permalink":"/post/前端框架开发【九】实现过渡动画","photos":[],"count_time":{"symbolsCount":"21k","symbolsTime":"19 mins."},"categories":[{"name":"VUE","slug":"VUE","count":9,"path":"api/categories/VUE.json"}],"tags":[{"name":"VUE 入门","slug":"VUE-入门","count":9,"path":"api/tags/VUE-入门.json"}],"author":{"name":"一小池勺","slug":"blog-author","avatar":"https://pic.imgdb.cn/item/65c339bd9f345e8d03bb301d.jpg","link":"/","description":"不要感受路，要赶路","socials":{"github":"https://gitee.com/zrblue","twitter":"","stackoverflow":"","wechat":"","qq":"","weibo":"https://weibo.com/u/3318213455","zhihu":"","csdn":"https://blog.csdn.net/zrblue?type=blog","juejin":"https://juejin.cn","customs":{}}}}}